syst_plugin/__init__.py
syst_plugin/plugin.py
syst_plugin/pyst_process.py
pytest_system_test_plugin-0.0.2.dist-info/LICENSE
pytest_system_test_plugin-0.0.2.dist-info/METADATA
pytest_system_test_plugin-0.0.2.dist-info/WHEEL
pytest_system_test_plugin-0.0.2.dist-info/entry_points.txt
pytest_system_test_plugin-0.0.2.dist-info/top_level.txt
pytest_system_test_plugin-0.0.2.dist-info/RECORD
