Metadata-Version: 2.1
Name: pytest-system-test-plugin
Version: 0.0.2
Summary: Pyst - Pytest System-Test Plugin
Home-page: https://gitlab.com/bitmuster/pytest_system_test_plugin
Author: Michael Abel
Author-email: python@bitmuster.org
License: UNKNOWN
Project-URL: GitLab, https://gitlab.com/bitmuster/pytest_system_test_plugin
Project-URL: GitHub, https://github.com/bitmuster/pytest_system_test_plugin
Project-URL: Examples, https://github.com/abelikt/pytest_system_test_plugin_test
Platform: UNKNOWN
Classifier: Framework :: Pytest
License-File: LICENSE
